{
    "family": "warframe-bot",
    "networkMode": "bridge",
    "executionRoleArn": "arn:aws:iam::580345014258:role/ap-south-1-discord",
    "containerDefinitions": [
        {
            "name": "warframe-bot",
            "image": "580345014258.dkr.ecr.ap-south-1.amazonaws.com/warframe_bot:latest",
            "cpu": 256,
            "memory": 128,
            "portMappings": [
                {
                    "containerPort": 80,
                    "hostPort": 80,
                    "protocol": "tcp"
                }
            ],
            "essential": true,
            "secrets": [
                {
                    "name": "TOKEN",
                    "valueFrom ": "warframe_bot_token"
                },
                {
                    "name": "GUILD",
                    "valueFrom": "warframe_india_server_name"
                },
                {
                    "name": "GENERAL_CHANNEL_ID",
                    "valueFrom": "general_channel_id"
                },
                {
                    "name": "GIVEAWAY_CHANNEL_ID",
                    "valueFrom": "giveaway_channel_id"
                },
                {
                    "name": "USER_ID",
                    "valueFrom": "test_user_id"
                }
            ]
        }
    ],
    "requiresCompatibilities": [
        "EC2"
    ]
}
